{
"type": "FeatureCollection",
"crs": { "type": "name", "properties": { "name": "urn:ogc:def:crs:OGC:1.3:CRS84" } },
"features": [
{ "type": "Feature", "properties": { "id": 1 }, "geometry": { "type": "Point", "coordinates": [ 28.329634165561977, -15.333968331277566, 1182.3 ] } },
{ "type": "Feature", "properties": { "id": 2 }, "geometry": { "type": "Point", "coordinates": [ 28.329635666851662, -15.333968602539498, 1182.15 ] } },
{ "type": "Feature", "properties": { "id": 3 }, "geometry": { "type": "Point", "coordinates": [ 28.329637158827577, -15.33396887385689, 1182.1 ] } },
{ "type": "Feature", "properties": { "id": 4 }, "geometry": { "type": "Point", "coordinates": [ 28.329638436358042, -15.333969110296218, 1182.1 ] } },
{ "type": "Feature", "properties": { "id": 5 }, "geometry": { "type": "Point", "coordinates": [ 28.329639713831341, -15.333969337697036, 1182.1 ] } },
{ "type": "Feature", "properties": { "id": 6 }, "geometry": { "type": "Point", "coordinates": [ 28.32964099130464, -15.333969565097837, 1182.1 ] } },
{ "type": "Feature", "properties": { "id": 7 }, "geometry": { "type": "Point", "coordinates": [ 28.329642418026985, -15.333969827765033, 1182.05 ] } },
{ "type": "Feature", "properties": { "id": 8 }, "geometry": { "type": "Point", "coordinates": [ 28.329643844749334, -15.333970090432221, 1182.0 ] } },
{ "type": "Feature", "properties": { "id": 9 }, "geometry": { "type": "Point", "coordinates": [ 28.329645495230917, -15.333970387921967, 1181.967 ] } },
{ "type": "Feature", "properties": { "id": 10 }, "geometry": { "type": "Point", "coordinates": [ 28.329647145712503, -15.333970685411696, 1181.933 ] } },
{ "type": "Feature", "properties": { "id": 11 }, "geometry": { "type": "Point", "coordinates": [ 28.329648805507869, -15.333970982845932, 1181.9 ] } },
{ "type": "Feature", "properties": { "id": 12 }, "geometry": { "type": "Point", "coordinates": [ 28.329650232230229, -15.333971245513068, 1181.85 ] } },
{ "type": "Feature", "properties": { "id": 13 }, "geometry": { "type": "Point", "coordinates": [ 28.329651658952592, -15.333971508180207, 1181.8 ] } },
{ "type": "Feature", "properties": { "id": 14 }, "geometry": { "type": "Point", "coordinates": [ 28.329652973738177, -15.333971744397536, 1181.867 ] } },
{ "type": "Feature", "properties": { "id": 15 }, "geometry": { "type": "Point", "coordinates": [ 28.32965427920999, -15.333971980670345, 1181.933 ] } },
{ "type": "Feature", "properties": { "id": 16 }, "geometry": { "type": "Point", "coordinates": [ 28.329655593995575, -15.333972216887657, 1182.0 ] } },
{ "type": "Feature", "properties": { "id": 17 }, "geometry": { "type": "Point", "coordinates": [ 28.329657020717949, -15.333972479554758, 1182.0 ] } },
{ "type": "Feature", "properties": { "id": 18 }, "geometry": { "type": "Point", "coordinates": [ 28.329658438069387, -15.333972733238815, 1182.0 ] } },
{ "type": "Feature", "properties": { "id": 19 }, "geometry": { "type": "Point", "coordinates": [ 28.329659864791765, -15.333972995905889, 1182.0 ] } },
{ "type": "Feature", "properties": { "id": 20 }, "geometry": { "type": "Point", "coordinates": [ 28.329661394022825, -15.333973267001198, 1182.033 ] } },
{ "type": "Feature", "properties": { "id": 21 }, "geometry": { "type": "Point", "coordinates": [ 28.329662923311055, -15.333973547135013, 1182.2 ] } },
{ "type": "Feature", "properties": { "id": 22 }, "geometry": { "type": "Point", "coordinates": [ 28.329664461913065, -15.333973827213338, 1182.3 ] } },
{ "type": "Feature", "properties": { "id": 23 }, "geometry": { "type": "Point", "coordinates": [ 28.329666009828845, -15.333974107236168, 1182.3 ] } },
{ "type": "Feature", "properties": { "id": 24 }, "geometry": { "type": "Point", "coordinates": [ 28.329667557744635, -15.333974387258991, 1182.3 ] } },
{ "type": "Feature", "properties": { "id": 25 }, "geometry": { "type": "Point", "coordinates": [ 28.329669096346652, -15.333974667337284, 1182.3 ] } }
]
}
